{
  "strategy": "relationship_aware",
  "query": "Who is Frodo?",
  "nodes": [
    {
      "id": "4:bea90507-3768-49ba-92f9-8e7bd4ce7692:1505",
      "labels": [
        "__KGBuilder__",
        "Character",
        "__Entity__"
      ],
      "properties": {
        "name": "Frodo Baggins"
      },
      "matched_in": [
        "name"
      ]
    },
    {
      "id": "4:bea90507-3768-49ba-92f9-8e7bd4ce7692:2015",
      "labels": [
        "Community"
      ],
      "properties": {}
    },
    {
      "id": "4:bea90507-3768-49ba-92f9-8e7bd4ce7692:1684",
      "labels": [
        "Community"
      ],
      "properties": {}
    },
    {
      "id": "4:bea90507-3768-49ba-92f9-8e7bd4ce7692:1964",
      "labels": [
        "Community"
      ],
      "properties": {}
    },
    {
      "id": "4:bea90507-3768-49ba-92f9-8e7bd4ce7692:1671",
      "labels": [
        "Community"
      ],
      "properties": {}
    },
    {
      "id": "4:bea90507-3768-49ba-92f9-8e7bd4ce7692:96",
      "labels": [
        "Community"
      ],
      "properties": {}
    },
    {
      "id": "4:bea90507-3768-49ba-92f9-8e7bd4ce7692:278",
      "labels": [
        "__KGBuilder__",
        "Character",
        "__Entity__"
      ],
      "properties": {}
    },
    {
      "id": "4:bea90507-3768-49ba-92f9-8e7bd4ce7692:84",
      "labels": [
        "__KGBuilder__",
        "Location",
        "__Entity__"
      ],
      "properties": {}
    },
    {
      "id": "4:bea90507-3768-49ba-92f9-8e7bd4ce7692:267",
      "labels": [
        "__KGBuilder__",
        "Chunk"
      ],
      "properties": {}
    }
  ],
  "relationships": [
    {
      "id": "5:bea90507-3768-49ba-92f9-8e7bd4ce7692:9176",
      "type": "BELONGS_TO_COMMUNITY",
      "properties": {}
    },
    {
      "id": "5:bea90507-3768-49ba-92f9-8e7bd4ce7692:9175",
      "type": "BELONGS_TO_COMMUNITY",
      "properties": {}
    },
    {
      "id": "5:bea90507-3768-49ba-92f9-8e7bd4ce7692:8667",
      "type": "BELONGS_TO_COMMUNITY",
      "properties": {}
    },
    {
      "id": "5:bea90507-3768-49ba-92f9-8e7bd4ce7692:6017",
      "type": "BELONGS_TO_COMMUNITY",
      "properties": {}
    },
    {
      "id": "5:bea90507-3768-49ba-92f9-8e7bd4ce7692:6013",
      "type": "BELONGS_TO_COMMUNITY",
      "properties": {}
    },
    {
      "id": "5:bea90507-3768-49ba-92f9-8e7bd4ce7692:4998",
      "type": "PARENT_OF",
      "properties": {}
    },
    {
      "id": "5:bea90507-3768-49ba-92f9-8e7bd4ce7692:4980",
      "type": "DWELLS_IN",
      "properties": {}
    },
    {
      "id": "5:bea90507-3768-49ba-92f9-8e7bd4ce7692:4471",
      "type": "FROM_CHUNK",
      "properties": {}
    }
  ],
  "paths": [],
  "execution_time": 0.08026933670043945,
  "total_results": 17,
  "metadata": {
    "entities_found": [
      "Frodo"
    ]
  }
}